git3Client/__init__.py
git3Client/__main__.py
git3Client/git3.py
git3Client/artifacts/contracts/GitFactory.sol/GitFactory.json
git3Client/artifacts/contracts/GitRepository.sol/GitRepository.json
git3Client/artifacts/contracts/facets/GitBranch.sol/GitBranch.json
git3Client/artifacts/contracts/facets/GitIssues.sol/GitIssues.json
git3Client/artifacts/contracts/facets/GitRepositoryManagement.sol/GitRepositoryManagement.json
git3Client/artifacts/contracts/facets/GitTips.sol/GitTips.json
git3Client/artifacts/contracts/factory_facets/RepositoryManagement.sol/RepositoryManagement.json
git3Client/artifacts/contracts/repo_facets/GitBranch.sol/GitBranch.json
git3Client/config/__init__.py
git3Client/config/config.py
git3Client/dlt/__init__.py
git3Client/dlt/contract.py
git3Client/dlt/provider.py
git3Client/dlt/repository.py
git3Client/dlt/storageClient.py
git3Client/dlt/user.py
git3Client/exceptions/NoABIFoundError.py
git3Client/exceptions/NoRepositoryError.py
git3Client/exceptions/__init__.py
git3Client/gitCommands/__init__.py
git3Client/gitCommands/add.py
git3Client/gitCommands/branch.py
git3Client/gitCommands/catFile.py
git3Client/gitCommands/checkout.py
git3Client/gitCommands/clone.py
git3Client/gitCommands/commit.py
git3Client/gitCommands/create.py
git3Client/gitCommands/diff.py
git3Client/gitCommands/fetch.py
git3Client/gitCommands/getAddress.py
git3Client/gitCommands/hashObject.py
git3Client/gitCommands/init.py
git3Client/gitCommands/lsFiles.py
git3Client/gitCommands/merge.py
git3Client/gitCommands/pull.py
git3Client/gitCommands/push.py
git3Client/gitCommands/status.py
git3Client/gitInternals/IndexEntry.py
git3Client/gitInternals/__init__.py
git3Client/gitInternals/fileMode.py
git3Client/gitInternals/gitCommit.py
git3Client/gitInternals/gitIndex.py
git3Client/gitInternals/gitObject.py
git3Client/gitInternals/gitTree.py
git3Client/utils/__init__.py
git3Client/utils/utils.py
git3Client-0.2.6.data/data/contractAbi/GitBranch.json
git3Client-0.2.6.dist-info/LICENSE
git3Client-0.2.6.dist-info/METADATA
git3Client-0.2.6.dist-info/WHEEL
git3Client-0.2.6.dist-info/entry_points.txt
git3Client-0.2.6.dist-info/top_level.txt
git3Client-0.2.6.dist-info/RECORD
