Metadata-Version: 2.1
Name: git3Client
Version: 0.2.6
Summary: Git3 Python client
Home-page: https://github.com/varkiwi/git3-client
Author: Jacek Varky
Author-email: jaca347@gmail.com
Classifier: Development Status :: 3 - Alpha
License-File: LICENSE
Requires-Dist: aiohttp (==3.8.1)
Requires-Dist: aiosignal (==1.2.0)
Requires-Dist: async-timeout (==4.0.2)
Requires-Dist: attrs (==20.2.0)
Requires-Dist: base58 (==2.0.1)
Requires-Dist: bitarray (==1.2.2)
Requires-Dist: bleach (==5.0.0)
Requires-Dist: certifi (==2020.6.20)
Requires-Dist: cffi (==1.15.0)
Requires-Dist: chardet (==3.0.4)
Requires-Dist: charset-normalizer (==2.0.12)
Requires-Dist: commonmark (==0.9.1)
Requires-Dist: cryptography (==36.0.2)
Requires-Dist: cytoolz (==0.12.1)
Requires-Dist: docutils (==0.18.1)
Requires-Dist: eth-abi (==2.1.1)
Requires-Dist: eth-account (==0.5.5)
Requires-Dist: eth-hash (==0.2.0)
Requires-Dist: eth-keyfile (==0.5.1)
Requires-Dist: eth-keys (==0.3.3)
Requires-Dist: eth-rlp (==0.2.1)
Requires-Dist: eth-typing (==2.2.2)
Requires-Dist: eth-utils (==1.9.5)
Requires-Dist: frozenlist (==1.3.0)
Requires-Dist: hexbytes (==0.2.1)
Requires-Dist: idna (==2.10)
Requires-Dist: importlib-metadata (==4.0.1)
Requires-Dist: importlib-resources (==3.0.0)
Requires-Dist: ipfshttpclient (==0.8.0a2)
Requires-Dist: jsonschema (==3.2.0)
Requires-Dist: keyring (==23.5.0)
Requires-Dist: lru-dict (==1.1.6)
Requires-Dist: multiaddr (==0.0.9)
Requires-Dist: multidict (==6.0.2)
Requires-Dist: netaddr (==0.8.0)
Requires-Dist: parsimonious (==0.8.1)
Requires-Dist: pkginfo (==1.8.2)
Requires-Dist: protobuf (==3.13.0)
Requires-Dist: pycparser (==2.21)
Requires-Dist: pycryptodome (==3.9.8)
Requires-Dist: Pygments (==2.11.2)
Requires-Dist: pyrsistent (==0.17.3)
Requires-Dist: readme-renderer (==34.0)
Requires-Dist: requests (==2.27.1)
Requires-Dist: requests-toolbelt (==0.9.1)
Requires-Dist: rfc3986 (==2.0.0)
Requires-Dist: rich (==12.2.0)
Requires-Dist: rlp (==2.0.0)
Requires-Dist: six (==1.15.0)
Requires-Dist: toolz (==0.11.1)
Requires-Dist: twine (==4.0.0)
Requires-Dist: typing-extensions (==4.2.0)
Requires-Dist: urllib3 (==1.26.9)
Requires-Dist: varint (==1.0.2)
Requires-Dist: web3 (==5.23.1)
Requires-Dist: webencodings (==0.5.1)
Requires-Dist: websockets (==9.1)
Requires-Dist: yarl (==1.7.2)
Requires-Dist: zipp (==3.3.1)
